dive-logger/__init__.py
dive-logger/logger.py
dive_logger-0.1.0.dist-info/licenses/LICENSE
tests/__init__.py
dive_logger-0.1.0.dist-info/METADATA
dive_logger-0.1.0.dist-info/WHEEL
dive_logger-0.1.0.dist-info/top_level.txt
dive_logger-0.1.0.dist-info/RECORD
