Metadata-Version: 2.4
Name: dive-logger
Version: 0.1.0
Summary: A colorful and feature-rich logging utility for Python
Author-email: Carlos Rivera <carlos@dive.ai>
License: MIT
Keywords: logging,logger,colored,color,debug
Classifier: Development Status :: 3 - Alpha
Classifier: Intended Audience :: Developers
Classifier: License :: OSI Approved :: MIT License
Classifier: Programming Language :: Python :: 3
Classifier: Programming Language :: Python :: 3.7
Classifier: Programming Language :: Python :: 3.8
Classifier: Programming Language :: Python :: 3.9
Classifier: Programming Language :: Python :: 3.10
Classifier: Programming Language :: Python :: 3.11
Classifier: Programming Language :: Python :: 3.12
Requires-Python: >=3.7
License-File: LICENSE
Dynamic: license-file
